Metadata-Version: 2.1
Name: chronologicon
Version: 5.5
Summary: A minimal time tracker
Home-page: https://github.com/rutherfordcraze/chronologicon
Author: Rutherford Craze
Author-email: rutherford@craze.co.uk
License: MIT
Platform: UNKNOWN
